{

    "defaultState": [{
        "stateId": "vimeo-video-state-test"
    }],
    "states": [{
        "id": "vimeo-video-state-test",
        "name": "Vimeo Video Test",
        "url": "/vimeo-video-test",
        "type": "video",
        "header": {},
        "footer": {},
        "onEnter": [],
        "onExit": [],
        "next": [],
        "onVideoEnd": [],
        "playerSettings": {
            "controls": "standard",
            "vimeoId"  : "2345579"
        },
        "personalizations": [],
        "cuePoints": []
    }]
}